{"title":"Combined feed","url":"https://Pelletan.github.io/feeds/all.xml","elements":[{"title":"La chanteuse Madonna fête ses 63 ans, ce lundi 16 août ! (Melody TV)","contents":"Déjà 63 ans pour l’incroyable chanteuse MADONNA dont la carrière&nbsp;a...","link":"https://www.melody.tv/actualite/la-chanteuse-madonna-fete-ses-63-ans-ce-lundi-16-aout","retrieved":1629097200000},{"title":"Sylvie Vartan fête ses 77 ans, ce dimanche 15 août (Melody TV)","contents":"Elle a enregistré 65 albums&nbsp;et 1500 chansons tout au long de...","link":"https://www.melody.tv/actualite/sylvie-vartan-fete-ses-77-ans-ce-dimanche-15-aout","retrieved":1629010800000},{"title":"Le chanteur David Hallyday fête ses 55 ans (Melody TV)","contents":"Le premier fils de Johnny HALLYDAY et de Sylvie VARTAN, passe...","link":"https://www.melody.tv/actualite/le-chanteur-david-hallyday-fete-ses-55-ans","retrieved":1628924400000},{"title":"Julien Lepers fête ses 72 ans, ce jeudi 12 août ! (Melody TV)","contents":"« C’est une question pour un champion ! », tout le...","link":"https://www.melody.tv/actualite/julien-lepers-fete-ses-72-ans-ce-jeudi-12-aout","retrieved":1628760360000},{"title":"L’acteur Daniel Auteuil sort son premier album (Melody TV)","contents":"Après l’humoriste Didier Bourbon, ex-membre des Inconnus,...","link":"https://www.melody.tv/actualite/l-acteur-daniel-auteuil-sort-son-premier-album","retrieved":1629308170611},{"title":"Le chanteur Calogero fête ses 50 ans ! (Melody TV)","contents":"En 2002, CALOGERO se fait connaître avec son titre \"En apesanteur\".&nbsp;Le...","link":"https://www.melody.tv/actualite/le-chanteur-calogero-fete-ses-50-ans","retrieved":1627635600000},{"title":"Bon anniversaire à Christian Delagrange ! (Melody TV)","contents":"\"Tendre Cathy\", \"J'aime la vie avec toi\", \"Les larmes aux yeux\",...","link":"https://www.melody.tv/actualite/bon-anniversaire-a-christian-delagrange","retrieved":1627462800000},{"title":"La tournée Johnny Symphonique Tour va sillonner dans la France (Melody TV)","contents":"Le 25 octobre 2019 sortait « Johnny », un album posthume...","link":"https://www.melody.tv/actualite/la-tournee-johnny-symphonique-tour-va-sillonner-dans-la-france","retrieved":1627030800000},{"title":"Melody moi tout : 5 anecdotes sur le crooner et chanteur Dany Brillant (Melody TV)","contents":"De «&nbsp;Suzette&nbsp;» à l’album hommage à Charles Aznavour,...","link":"https://www.melody.tv/actualite/melody-moi-tout-5-anecdotes-sur-le-crooner-et-chanteur-dany-brillant","retrieved":1626773520000},{"title":"Zizi Jeanmaire, l’actrice (Melody TV)","contents":"Connue pour son talent de danseuse, mais aussi pour sa gouaille...","link":"https://www.melody.tv/actualite/zizi-jeanmaire-l-actrice","retrieved":1626512400000},{"title":"Zizi Jeanmaire : figure emblématique des revues (Melody TV)","contents":"Il y a pile un an, le 17 juillet 2020, une grande dame de la...","link":"https://www.melody.tv/actualite/zizi-jeanmaire-figure-emblematique-des-revues","retrieved":1626426720000},{"title":"Disquaire day 2021 le 17 juillet (Melody TV)","contents":"C’est la journée des disquaires indépendants ce samedi 17...","link":"https://www.melody.tv/actualite/disquaire-day-2021-le-17-juillet","retrieved":1626339600000},{"title":"L'animatrice Dorothée fête ses 68 ans ! (Melody TV)","contents":"On ne la présente plus ! Animatrice de Recré A2 de 1978 à...","link":"https://www.melody.tv/actualite/lanimatrice-dorothee-fete-ses-68-ans","retrieved":1626253200000},{"title":"Disparition de la réalisatrice Marion Sarraut, à l’âge de 82 ans (Melody TV)","contents":"&nbsp;Célèbre pour ses shows de variétés et réalisatrice de&nbsp;« Numéro...","link":"https://www.melody.tv/actualite/disparition-de-la-realisatrice-marion-sarraut-a-l-age-de-82-ans","retrieved":1629308170628},{"title":"Les plus belles affiches du Festival de Cannes (Melody TV)","contents":"Exceptionnellement cette année, le Festival de Cannes ne se...","link":"https://www.melody.tv/actualite/les-plus-belles-affiches-du-festival-de-cannes","retrieved":1625907600000},{"title":"Pierre Perret fête ses 87 ans ! (Melody TV)","contents":"L'interprète de \"Lily\", \"Mon p'tit loup\" reconnaissable avec...","link":"https://www.melody.tv/actualite/pierre-perret-fete-ses-87-ans","retrieved":1625821200000},{"title":"Ringo Starr : l'ex batteur des Beatles a 81 ans (Melody TV)","contents":"C'est l'anniversaire de&nbsp;Ringo STARR&nbsp;! Mondialement connu pour...","link":"https://www.melody.tv/actualite/ringo-starr-lex-batteur-des-beatles-a-81-ans","retrieved":1625648400000},{"title":"Flora Mae Hunter (Wikipedia — did you know?)","contents":"... that the cooking of <b><a href=\"/wiki/Flora_Mae_Hunter\" title=\"Flora Mae Hunter\">Flora Mae Hunter</a></b> <i>(pictured)</i> was enjoyed so much by the <a href=\"/wiki/Wallis_Simpson\" title=\"Wallis Simpson\">Duchess of Windsor</a> that she gained weight on her visits to the plantation where Hunter worked?","link":"https://en.wikipedia.org/wiki/Flora_Mae_Hunter","retrieved":1629308173720},{"title":"pronoun avoidance (Wikipedia — did you know?)","contents":"... that in <a href=\"/wiki/Indonesian_language\" title=\"Indonesian language\">Indonesian</a>, a language featuring <b><a href=\"/wiki/Pronoun_avoidance\" title=\"Pronoun avoidance\">pronoun avoidance</a></b>, a common polite way to address someone else is \"father\" or \"mother\", instead of \"you\"?","link":"https://en.wikipedia.org/wiki/Pronoun_avoidance","retrieved":1629308173720},{"title":"Gottfried Hornik (Wikipedia — did you know?)","contents":"... that <b><a href=\"/wiki/Gottfried_Hornik\" title=\"Gottfried Hornik\">Gottfried Hornik</a></b>, a <a href=\"/wiki/Baritone\" title=\"Baritone\">baritone</a> at the <a href=\"/wiki/Vienna_State_Opera\" title=\"Vienna State Opera\">Vienna State Opera</a> for 25 years, appeared in his signature role of <a href=\"/wiki/Die_Meistersinger_von_N%C3%BCrnberg\" title=\"Die Meistersinger von Nürnberg\">Beckmesser</a> from <a href=\"/wiki/Theater_Aachen\" title=\"Theater Aachen\">Aachen</a> and <a href=\"/wiki/Liceu\" title=\"Liceu\">Barcelona</a> in 1976 to the <a href=\"/wiki/Municipal_Theatre_of_Santiago\" title=\"Municipal Theatre of Santiago\">Municipal Theatre of Santiago</a> in 2001?","link":"https://en.wikipedia.org/wiki/Gottfried_Hornik","retrieved":1629308173721},{"title":"Beaux-Arts Apartments (Wikipedia — did you know?)","contents":"... that the <b><a href=\"/wiki/Beaux-Arts_Apartments\" title=\"Beaux-Arts Apartments\">Beaux-Arts Apartments</a></b> never went into foreclosure despite being completed at the start of the Great Depression?","link":"https://en.wikipedia.org/wiki/Beaux-Arts_Apartments","retrieved":1629308173721},{"title":"The Fifth Doll (Wikipedia — did you know?)","contents":"... that <a href=\"/wiki/Charlie_N._Holmberg\" title=\"Charlie N. Holmberg\">Charlie N. Holmberg</a>'s idea for <i><b><a href=\"/wiki/The_Fifth_Doll\" title=\"The Fifth Doll\">The Fifth Doll</a></b></i> began with a writing exercise to develop a system of magic for a household item?","link":"https://en.wikipedia.org/wiki/The_Fifth_Doll","retrieved":1629308173721},{"title":"PMA (Wikipedia — did you know?)","contents":"... that the <a href=\"/wiki/All_Time_Low\" title=\"All Time Low\">All Time Low</a> song \"<b><a href=\"/wiki/PMA_(All_Time_Low_song)\" title=\"PMA (All Time Low song)\">PMA</a></b>\" features guest vocals from Heather Baron-Gracie of the British band <a href=\"/wiki/Pale_Waves\" title=\"Pale Waves\">Pale Waves</a>?","link":"https://en.wikipedia.org/wiki/PMA_(All_Time_Low_song)","retrieved":1629308173722},{"title":"Song Kok Hoo (Wikipedia — did you know?)","contents":"... that <b><a href=\"/wiki/Song_Kok_Hoo\" title=\"Song Kok Hoo\">Song Kok Hoo</a></b> was the first Asian <a href=\"/wiki/Deputy_Commissioner_of_Police_(Singapore)\" title=\"Deputy Commissioner of Police (Singapore)\">deputy commissioner of police</a> in Singapore?","link":"https://en.wikipedia.org/wiki/Song_Kok_Hoo","retrieved":1629308173724},{"title":"Schloss Gripsholm (Wikipedia — did you know?)","contents":"... that <i><b><a href=\"/wiki/Schloss_Gripsholm\" title=\"Schloss Gripsholm\">Schloss Gripsholm</a></b></i> was dedicated by author <a href=\"/wiki/Kurt_Tucholsky\" title=\"Kurt Tucholsky\">Kurt Tucholsky</a> to a license plate number?","link":"https://en.wikipedia.org/wiki/Schloss_Gripsholm","retrieved":1629308173724}]}